tests/__init__.py
tests/test_black_scholes.py
tests/test_cboe_margin.py
tests/test_data.py
tests/test_famafrench.py
tests/test_fixed_income.py
tests/test_functional.py
tests/test_portfolio.py
tests/test_visualization.py
toolkit/__init__.py
toolkit/asset_class.py
toolkit/black_scholes.py
toolkit/cboe_margin.py
toolkit/data.py
toolkit/fixed_income.py
toolkit/functional.py
toolkit/portfolio.py
toolkit/visualization.py
fintoolkit-0.0.20.dist-info/METADATA
fintoolkit-0.0.20.dist-info/WHEEL
fintoolkit-0.0.20.dist-info/RECORD
