Metadata-Version: 2.4
Name: fintoolkit
Version: 0.0.20
Summary: Financial Toolkit
Project-URL: Homepage, https://github.com/chris-kc-cheng/financial-toolkit
Project-URL: Bug Tracker, https://github.com/chris-kc-cheng/financial-toolkit/issues
Author-email: Chris Cheng <kc1116@gmail.com>
Classifier: License :: OSI Approved :: MIT License
Classifier: Operating System :: OS Independent
Classifier: Programming Language :: Python :: 3
Requires-Python: >=3.11
Requires-Dist: matplotlib
Requires-Dist: numpy
Requires-Dist: pandas
Requires-Dist: pandas-datareader
Requires-Dist: scikit-learn
Requires-Dist: scipy
Requires-Dist: statsmodels
Requires-Dist: yfinance
